py_scibec/__init__.py
py_scibec/bec.py
py_scibec/exceptions.py
py_scibec-1.15.0.dist-info/METADATA
py_scibec-1.15.0.dist-info/WHEEL
py_scibec-1.15.0.dist-info/top_level.txt
py_scibec-1.15.0.dist-info/RECORD
