Metadata-Version: 2.1
Name: py-scibec
Version: 1.15.0
Summary: Python Client for the BEC REST API
Home-page: https://gitlab.psi.ch/bec/scibec
Project-URL: Bug Tracker, https://gitlab.psi.ch/bec/scibec/issues
Classifier: Programming Language :: Python :: 3
Classifier: Development Status :: 3 - Alpha
Classifier: Topic :: Scientific/Engineering
Requires-Python: >=3.10
Requires-Dist: requests
Requires-Dist: tqdm
Requires-Dist: py-scibec-openapi-client
Provides-Extra: dev
Requires-Dist: pytest; extra == "dev"
Requires-Dist: pytest-random-order; extra == "dev"
Requires-Dist: coverage; extra == "dev"
Requires-Dist: black; extra == "dev"
Requires-Dist: pylint; extra == "dev"
Requires-Dist: python-dotenv; extra == "dev"
